[
    {
        "txt": "I would like access to the Choral AI Dataset/Model.",
        "statement_id": 0,
        "created": "2024-09-23T14:28:54.187000Z",
        "tweet_id": null,
        "quote_src_url": null,
        "is_seed": true,
        "is_meta": false,
        "lang": "en",
        "participant_id": 0,
        "velocity": 1,
        "moderated": 1,
        "active": true,
        "agree_count": 21,
        "disagree_count": 7,
        "pass_count": 5,
        "count": 33,
        "conversation_id": "6s8bxtsfrs",
        "datetime": null
    },
    {
        "txt": "My choir would like to use the Choral AI Dataset/Model.",
        "statement_id": 1,
        "created": "2024-09-23T14:29:00.450000Z",
        "tweet_id": null,
        "quote_src_url": null,
        "is_seed": true,
        "is_meta": false,
        "lang": "en",
        "participant_id": 0,
        "velocity": 1,
        "moderated": 1,
        "active": true,
        "agree_count": 18,
        "disagree_count": 5,
        "pass_count": 11,
        "count": 34,
        "conversation_id": "6s8bxtsfrs",
        "datetime": null
    },
    {
        "txt": "I think the Choral AI Dataset/Model should be available for researchers to use in research projects.",
        "statement_id": 2,
        "created": "2024-09-23T14:29:12.423000Z",
        "tweet_id": null,
        "quote_src_url": null,
        "is_seed": true,
        "is_meta": false,
        "lang": "en",
        "participant_id": 0,
        "velocity": 1,
        "moderated": 1,
        "active": true,
        "agree_count": 27,
        "disagree_count": 1,
        "pass_count": 5,
        "count": 33,
        "conversation_id": "6s8bxtsfrs",
        "datetime": null
    },
    {
        "txt": "I think the Choral AI Dataset/Model should be available for teachers to use for educational purposes.",
        "statement_id": 3,
        "created": "2024-09-23T14:29:31.903000Z",
        "tweet_id": null,
        "quote_src_url": null,
        "is_seed": true,
        "is_meta": false,
        "lang": "en",
        "participant_id": 0,
        "velocity": 1,
        "moderated": 1,
        "active": true,
        "agree_count": 29,
        "disagree_count": 0,
        "pass_count": 4,
        "count": 33,
        "conversation_id": "6s8bxtsfrs",
        "datetime": null
    },
    {
        "txt": "I think the Choral AI Dataset/Model should be available for singers/choirs to use in rehearsal settings.",
        "statement_id": 4,
        "created": "2024-09-23T14:29:38.526000Z",
        "tweet_id": null,
        "quote_src_url": null,
        "is_seed": true,
        "is_meta": false,
        "lang": "en",
        "participant_id": 0,
        "velocity": 1,
        "moderated": 1,
        "active": true,
        "agree_count": 23,
        "disagree_count": 1,
        "pass_count": 9,
        "count": 33,
        "conversation_id": "6s8bxtsfrs",
        "datetime": null
    },
    {
        "txt": "I think the Choral AI Dataset/Model model should be available for singers/choirs to use for public performances.",
        "statement_id": 5,
        "created": "2024-09-23T14:29:44.756000Z",
        "tweet_id": null,
        "quote_src_url": null,
        "is_seed": true,
        "is_meta": false,
        "lang": "en",
        "participant_id": 0,
        "velocity": 1,
        "moderated": 1,
        "active": true,
        "agree_count": 17,
        "disagree_count": 6,
        "pass_count": 11,
        "count": 34,
        "conversation_id": "6s8bxtsfrs",
        "datetime": null
    },
    {
        "txt": "I think the Choral AI Dataset/Model should be available for artists to use to create new art projects or exhibitions.",
        "statement_id": 6,
        "created": "2024-09-23T14:29:50.456000Z",
        "tweet_id": null,
        "quote_src_url": null,
        "is_seed": true,
        "is_meta": false,
        "lang": "en",
        "participant_id": 0,
        "velocity": 1,
        "moderated": 1,
        "active": true,
        "agree_count": 22,
        "disagree_count": 3,
        "pass_count": 7,
        "count": 32,
        "conversation_id": "6s8bxtsfrs",
        "datetime": null
    },
    {
        "txt": "I think the Choral AI Dataset/Model should be available for artists to use to generate new music.",
        "statement_id": 7,
        "created": "2024-09-23T14:30:01.811000Z",
        "tweet_id": null,
        "quote_src_url": null,
        "is_seed": true,
        "is_meta": false,
        "lang": "en",
        "participant_id": 0,
        "velocity": 1,
        "moderated": 1,
        "active": true,
        "agree_count": 16,
        "disagree_count": 7,
        "pass_count": 10,
        "count": 33,
        "conversation_id": "6s8bxtsfrs",
        "datetime": null
    },
    {
        "txt": "I think the Choral AI Dataset/Model should be available for public use for any use case.",
        "statement_id": 8,
        "created": "2024-09-23T14:30:07.584000Z",
        "tweet_id": null,
        "quote_src_url": null,
        "is_seed": true,
        "is_meta": false,
        "lang": "en",
        "participant_id": 0,
        "velocity": 1,
        "moderated": 1,
        "active": true,
        "agree_count": 3,
        "disagree_count": 22,
        "pass_count": 8,
        "count": 33,
        "conversation_id": "6s8bxtsfrs",
        "datetime": null
    },
    {
        "txt": "I think the Choral AI Dataset/Model should be available for developers to create other Choral AI models.\n",
        "statement_id": 9,
        "created": "2024-09-23T14:30:11.632000Z",
        "tweet_id": null,
        "quote_src_url": null,
        "is_seed": true,
        "is_meta": false,
        "lang": "en",
        "participant_id": 0,
        "velocity": 1,
        "moderated": 1,
        "active": true,
        "agree_count": 10,
        "disagree_count": 10,
        "pass_count": 12,
        "count": 32,
        "conversation_id": "6s8bxtsfrs",
        "datetime": null
    },
    {
        "txt": "I think the Choral AI Dataset/Model should be available for commercial and profit-generating use cases.\n",
        "statement_id": 10,
        "created": "2024-09-23T14:30:24.939000Z",
        "tweet_id": null,
        "quote_src_url": null,
        "is_seed": true,
        "is_meta": false,
        "lang": "en",
        "participant_id": 0,
        "velocity": 1,
        "moderated": 1,
        "active": true,
        "agree_count": 7,
        "disagree_count": 20,
        "pass_count": 6,
        "count": 33,
        "conversation_id": "6s8bxtsfrs",
        "datetime": null
    },
    {
        "txt": "I think the Choral AI Dataset/Model should ONLY be available for non-profit use cases.\n",
        "statement_id": 11,
        "created": "2024-09-23T14:30:30.476000Z",
        "tweet_id": null,
        "quote_src_url": null,
        "is_seed": true,
        "is_meta": false,
        "lang": "en",
        "participant_id": 0,
        "velocity": 1,
        "moderated": 1,
        "active": true,
        "agree_count": 19,
        "disagree_count": 10,
        "pass_count": 5,
        "count": 34,
        "conversation_id": "6s8bxtsfrs",
        "datetime": null
    },
    {
        "txt": "I think it\u2019s important that any user of the Choral AI Dataset/Model credits my choir in an attribution statement.\n",
        "statement_id": 12,
        "created": "2024-09-23T14:30:36.061000Z",
        "tweet_id": null,
        "quote_src_url": null,
        "is_seed": true,
        "is_meta": false,
        "lang": "en",
        "participant_id": 0,
        "velocity": 1,
        "moderated": 1,
        "active": true,
        "agree_count": 26,
        "disagree_count": 2,
        "pass_count": 5,
        "count": 33,
        "conversation_id": "6s8bxtsfrs",
        "datetime": null
    },
    {
        "txt": "I think it\u2019s important that if any future use case of the Choral AI Dataset/Model generates profit that my choir receives a fee.\n",
        "statement_id": 13,
        "created": "2024-09-23T14:30:53.397000Z",
        "tweet_id": null,
        "quote_src_url": null,
        "is_seed": true,
        "is_meta": false,
        "lang": "en",
        "participant_id": 0,
        "velocity": 1,
        "moderated": 1,
        "active": true,
        "agree_count": 24,
        "disagree_count": 3,
        "pass_count": 6,
        "count": 33,
        "conversation_id": "6s8bxtsfrs",
        "datetime": null
    },
    {
        "txt": "I think users should be able to create new models from the Choral AI Dataset/Model, for example by adding new choral data or to adapt the style.\n",
        "statement_id": 14,
        "created": "2024-09-23T14:30:56.411000Z",
        "tweet_id": null,
        "quote_src_url": null,
        "is_seed": true,
        "is_meta": false,
        "lang": "en",
        "participant_id": 0,
        "velocity": 1,
        "moderated": 1,
        "active": true,
        "agree_count": 19,
        "disagree_count": 3,
        "pass_count": 12,
        "count": 34,
        "conversation_id": "6s8bxtsfrs",
        "datetime": null
    },
    {
        "txt": "I think new models created from the Choral AI Dataset/Model should keep the same license terms (e.g. \u201cfor non-commercial uses only\u201d if that is selected for the Choral AI Dataset/Model).\n",
        "statement_id": 15,
        "created": "2024-09-23T14:31:06.907000Z",
        "tweet_id": null,
        "quote_src_url": null,
        "is_seed": true,
        "is_meta": false,
        "lang": "en",
        "participant_id": 0,
        "velocity": 1,
        "moderated": 1,
        "active": true,
        "agree_count": 26,
        "disagree_count": 0,
        "pass_count": 6,
        "count": 32,
        "conversation_id": "6s8bxtsfrs",
        "datetime": null
    },
    {
        "txt": "I think the Choral AI Dataset should be shared publicly for use by other users.\n",
        "statement_id": 16,
        "created": "2024-09-23T14:31:10.958000Z",
        "tweet_id": null,
        "quote_src_url": null,
        "is_seed": true,
        "is_meta": false,
        "lang": "en",
        "participant_id": 0,
        "velocity": 1,
        "moderated": 1,
        "active": true,
        "agree_count": 10,
        "disagree_count": 14,
        "pass_count": 9,
        "count": 33,
        "conversation_id": "6s8bxtsfrs",
        "datetime": null
    },
    {
        "txt": "I think users of the Choral AI Dataset should share their name and contact information.\n",
        "statement_id": 17,
        "created": "2024-09-23T14:31:14.176000Z",
        "tweet_id": null,
        "quote_src_url": null,
        "is_seed": true,
        "is_meta": false,
        "lang": "en",
        "participant_id": 0,
        "velocity": 1,
        "moderated": 1,
        "active": true,
        "agree_count": 16,
        "disagree_count": 7,
        "pass_count": 10,
        "count": 33,
        "conversation_id": "6s8bxtsfrs",
        "datetime": null
    },
    {
        "txt": "I think access to the Choral AI Dataset should be shared with users who agree to comply with our model/dataset license terms.\n",
        "statement_id": 18,
        "created": "2024-09-23T14:31:17.253000Z",
        "tweet_id": null,
        "quote_src_url": null,
        "is_seed": true,
        "is_meta": false,
        "lang": "en",
        "participant_id": 0,
        "velocity": 1,
        "moderated": 1,
        "active": true,
        "agree_count": 30,
        "disagree_count": 0,
        "pass_count": 3,
        "count": 33,
        "conversation_id": "6s8bxtsfrs",
        "datetime": null
    },
    {
        "txt": "I think access to the Choral AI Dataset should be gated by a trusted intermediary who can vet requests by other users.\n",
        "statement_id": 19,
        "created": "2024-09-23T14:31:20.390000Z",
        "tweet_id": null,
        "quote_src_url": null,
        "is_seed": true,
        "is_meta": false,
        "lang": "en",
        "participant_id": 0,
        "velocity": 1,
        "moderated": 1,
        "active": true,
        "agree_count": 25,
        "disagree_count": 1,
        "pass_count": 7,
        "count": 33,
        "conversation_id": "6s8bxtsfrs",
        "datetime": null
    },
    {
        "txt": "test",
        "statement_id": 20,
        "created": "2024-09-23T15:45:12.807000Z",
        "tweet_id": null,
        "quote_src_url": null,
        "is_seed": false,
        "is_meta": false,
        "lang": "en",
        "participant_id": 0,
        "velocity": 1,
        "moderated": 0,
        "active": false,
        "agree_count": 1,
        "disagree_count": 0,
        "pass_count": 0,
        "count": 1,
        "conversation_id": "6s8bxtsfrs",
        "datetime": null
    },
    {
        "txt": "All very exciting!!!",
        "statement_id": 21,
        "created": "2024-09-23T17:00:42.486000Z",
        "tweet_id": null,
        "quote_src_url": null,
        "is_seed": false,
        "is_meta": false,
        "lang": "en",
        "participant_id": 2,
        "velocity": 1,
        "moderated": 0,
        "active": false,
        "agree_count": 1,
        "disagree_count": 0,
        "pass_count": 0,
        "count": 1,
        "conversation_id": "6s8bxtsfrs",
        "datetime": null
    },
    {
        "txt": "Clear and able to be understood by those who don\u2019t know the project",
        "statement_id": 22,
        "created": "2024-10-02T16:28:01.873000Z",
        "tweet_id": null,
        "quote_src_url": null,
        "is_seed": false,
        "is_meta": false,
        "lang": "en",
        "participant_id": 10,
        "velocity": 1,
        "moderated": 0,
        "active": false,
        "agree_count": 1,
        "disagree_count": 0,
        "pass_count": 0,
        "count": 1,
        "conversation_id": "6s8bxtsfrs",
        "datetime": null
    },
    {
        "txt": "Need to learn from https://www.islingtontribune.co.uk/article/kids-who-didnt-need-no-education-enjoy-yet-another-round-of-royalties",
        "statement_id": 23,
        "created": "2024-10-02T17:39:47.590000Z",
        "tweet_id": null,
        "quote_src_url": null,
        "is_seed": false,
        "is_meta": false,
        "lang": "en",
        "participant_id": 13,
        "velocity": 1,
        "moderated": 0,
        "active": false,
        "agree_count": 1,
        "disagree_count": 0,
        "pass_count": 0,
        "count": 1,
        "conversation_id": "6s8bxtsfrs",
        "datetime": null
    },
    {
        "txt": "Don't know",
        "statement_id": 24,
        "created": "2024-10-02T18:29:16.849000Z",
        "tweet_id": null,
        "quote_src_url": null,
        "is_seed": false,
        "is_meta": false,
        "lang": "en",
        "participant_id": 14,
        "velocity": 1,
        "moderated": 0,
        "active": false,
        "agree_count": 1,
        "disagree_count": 0,
        "pass_count": 0,
        "count": 1,
        "conversation_id": "6s8bxtsfrs",
        "datetime": null
    },
    {
        "txt": "Terms for use  of Choral AI Dataset & Model to be reviewed periodically to ensure they're still fit for purpose and any misuse to be noted.",
        "statement_id": 25,
        "created": "2024-10-02T18:44:54.961000Z",
        "tweet_id": null,
        "quote_src_url": null,
        "is_seed": false,
        "is_meta": false,
        "lang": "en",
        "participant_id": 15,
        "velocity": 1,
        "moderated": 1,
        "active": true,
        "agree_count": 17,
        "disagree_count": 0,
        "pass_count": 2,
        "count": 19,
        "conversation_id": "6s8bxtsfrs",
        "datetime": null
    },
    {
        "txt": "In the UK, the noun licence should be spelt with two Cs.",
        "statement_id": 26,
        "created": "2024-10-03T06:12:03.833000Z",
        "tweet_id": null,
        "quote_src_url": null,
        "is_seed": false,
        "is_meta": false,
        "lang": "en",
        "participant_id": 20,
        "velocity": 1,
        "moderated": 0,
        "active": false,
        "agree_count": 1,
        "disagree_count": 0,
        "pass_count": 0,
        "count": 1,
        "conversation_id": "6s8bxtsfrs",
        "datetime": null
    },
    {
        "txt": "0",
        "statement_id": 27,
        "created": "2024-10-03T07:01:22.797000Z",
        "tweet_id": null,
        "quote_src_url": null,
        "is_seed": false,
        "is_meta": false,
        "lang": "und",
        "participant_id": 21,
        "velocity": 1,
        "moderated": 0,
        "active": false,
        "agree_count": 1,
        "disagree_count": 0,
        "pass_count": 0,
        "count": 1,
        "conversation_id": "6s8bxtsfrs",
        "datetime": null
    },
    {
        "txt": "The data should become part of Serpentine Galleries Archives.",
        "statement_id": 28,
        "created": "2024-10-03T09:53:38.708000Z",
        "tweet_id": null,
        "quote_src_url": null,
        "is_seed": false,
        "is_meta": false,
        "lang": "en",
        "participant_id": 23,
        "velocity": 1,
        "moderated": 1,
        "active": true,
        "agree_count": 11,
        "disagree_count": 0,
        "pass_count": 2,
        "count": 13,
        "conversation_id": "6s8bxtsfrs",
        "datetime": null
    },
    {
        "txt": "Folks involved in the project should be kept up-to-date on usage of their data.",
        "statement_id": 29,
        "created": "2024-10-06T21:12:33.851000Z",
        "tweet_id": null,
        "quote_src_url": null,
        "is_seed": false,
        "is_meta": false,
        "lang": "en",
        "participant_id": 31,
        "velocity": 1,
        "moderated": 1,
        "active": true,
        "agree_count": 3,
        "disagree_count": 0,
        "pass_count": 1,
        "count": 4,
        "conversation_id": "6s8bxtsfrs",
        "datetime": null
    },
    {
        "txt": "Agree",
        "statement_id": 30,
        "created": "2024-10-07T21:37:04.014000Z",
        "tweet_id": null,
        "quote_src_url": null,
        "is_seed": false,
        "is_meta": false,
        "lang": "en",
        "participant_id": 33,
        "velocity": 1,
        "moderated": 0,
        "active": false,
        "agree_count": 1,
        "disagree_count": 0,
        "pass_count": 0,
        "count": 1,
        "conversation_id": "6s8bxtsfrs",
        "datetime": null
    }
]